shiro/__init__.py
shiro/exceptions.py
shiro/jwa/__init__.py
shiro/jwa/jwk/__init__.py
shiro/jwa/jwk/base.py
shiro/jwa/jwk/ec.py
shiro/jwa/jwk/oct.py
shiro/jwa/jwk/rsa.py
shiro/jwa/jws/__init__.py
shiro/jwa/jws/base.py
shiro/jwa/jws/ec.py
shiro/jwa/jws/hmac.py
shiro/jwa/jws/none.py
shiro/jwa/jws/rsa_pkcs.py
shiro/jwa/jws/rsa_pss.py
shiro/jwk/__init__.py
shiro/jwk/jwk.py
shiro/jwk/jwks.py
shiro/jws/__init__.py
shiro/jws/header.py
shiro/jws/jws.py
shiro/jwt/__init__.py
shiro/jwt/claims.py
shiro/jwt/jwt.py
shiro-0.2.2.dist-info/LICENSE
shiro-0.2.2.dist-info/WHEEL
shiro-0.2.2.dist-info/METADATA
shiro-0.2.2.dist-info/RECORD
