Metadata-Version: 2.1
Name: shiro
Version: 0.2.2
Summary: JOSE implementation for Python.
Home-page: https://github.com/revensky/shiro
License: MIT
Keywords: JOSE,Json Web Signature,Json Web Encryption,Json Web Key,Json Web Token
Author: Eduardo Rezende
Author-email: eduardorbr7@gmail.com
Requires-Python: >=3.8,<4.0
Classifier: Development Status :: 4 - Beta
Classifier: Environment :: Web Environment
Classifier: Intended Audience :: Developers
Classifier: License :: OSI Approved :: MIT License
Classifier: Operating System :: OS Independent
Classifier: Programming Language :: Python :: 3
Classifier: Programming Language :: Python :: 3.8
Classifier: Programming Language :: Python :: 3.9
Classifier: Typing :: Typed
Requires-Dist: cryptography (>=3.1.1,<4.0.0)
Requires-Dist: fulldict (>=0.1.0,<0.2.0)
Requires-Dist: revensky.webtools (>=1.0.0,<2.0.0)
Project-URL: Repository, https://github.com/revensky/shiro.git
